[
  {
    "id": "ui-injection-demo",
    "name": "UI Injection Demo",
    "description": "Demonstrates native React component injection for dashboard widgets and system settings panels.",
    "author": "OpenTicket Team",
    "developer": {
      "name": "OpenTicket Team",
      "email": "dev@cyber-sec.space",
      "website": "https://openticket.cyber-sec.space"
    },
    "repositoryUrl": "https://github.com/Cyber-Sec-Space/openticket-plugin-registry",
    "icon": "layout",
    "latestVersion": "1.0.0",
    "versions": {
      "1.0.0": {
        "sourceType": "registry",
        "supportedPluginApiVersion": [
          ">=1.1.0"
        ],
        "integritySha256": "db93640c5954a014d06bc2b5642bba8163ea4bd8a324c2d830947b3529cbf85e",
        "requestedPermissions": [
          "VIEW_INCIDENTS_ALL"
        ],
        "dependsOn": [],
        "options": {
          "renderCondition": "always"
        },
        "configSchema": [
          {
            "key": "ENABLE_DEMO_MODE",
            "type": "boolean",
            "label": "Enable Settings Panel Interactive Demo Mode",
            "required": false
          }
        ]
      }
    }
  }
]